{
	"child":{
		"顺其自然":{
			"height_monthly_growth":0.39,
			"weight_monthly_growth":0.26,
			"bust_monthly_growth":0.3,
			"waist_monthly_growth":0.15,
			"hip_monthly_growth":0.33,
			"stamina_monthly_growth":0,
			"height_annual_growth":4.68,
			"weight_annual_growth":3.12,
			"bust_annual_growth":3.6,
			"waist_annual_growth":1.8,
			"hip_annual_growth":3.96,
			"stamina_annual_growth":0
		},
		"活泼取向":{
			"height_monthly_growth":0.5,
			"weight_monthly_growth":0.7,
			"bust_monthly_growth":0.4,
			"waist_monthly_growth":0.55,
			"hip_monthly_growth":0.4,
			"stamina_monthly_growth":2.5,
			"height_annual_growth":6,
			"weight_annual_growth":8.4,
			"bust_annual_growth":4.8,
			"waist_annual_growth":6.6,
			"hip_annual_growth":4.8,
			"stamina_annual_growth":30},
		"娴静取向":{},
		"进行减肥":{}
	},
	"teen":{
		""
	},
	"adult":{
		""
	}
}
