[
	{
		"id":"c01",
		"name":"常服",
		"description":"日常穿着的服装",
		"types":"CLOTHES",
		"prices":100,
		"can_use":true,
		"important":true
	},
	{
		"id":"c02",
		"name":"夏季服",
		"description":"夏季穿着的服装",
		"types":"CLOTHES",
		"prices":70,
		"can_use":true,
		"important":true
	},
	{
		"id":"c03",
		"name":"冬季服",
		"description":"冬季穿着的服装",
		"types":"CLOTHES",
		"prices":120,
		"can_use":true,
		"important":true
	},
	{
		"id":"c04",
		"name":"洋装",
		"description":"可以增加气质的洋装",
		"types":"CLOTHES",
		"prices":500,
		"can_use":true,
		"important":true
	},
	{
		"id":"c05",
		"name":"丝质洋装",
		"description":"更有气质的丝质洋装",
		"types":"CLOTHES",
		"prices":2000,
		"can_use":true,
		"important":true
	},
	{
		"id":"c07",
		"name":"武术服",
		"description":"适合练武的服装",
		"types":"CLOTHES",
		"prices":600,
		"can_use":true,
		"important":true
	},
	{
		"id":"c12",
		"name":"修道服",
		"description":"修女的修道服",
		"types":"CLOTHES",
		"prices":0,
		"can_use":true,
		"important":true
	},
	{
		"id":"c15",
		"name":"不良装扮",
		"description":"不良少女的装扮",
		"types":"CLOTHES",
		"prices":0,
		"can_use":true,
		"important":true
	},
	{
		"id":"c16",
		"name":"睡衣",
		"description":"睡衣",
		"types":"CLOTHES",
		"prices":0,
		"can_use":true,
		"important":true
	}
]
